Workbook

Sheet README
A1: B Active — Product & Pricing Master (VAT-inclusive)
A2: Revised for 12% VAT (prices marked up to absorb VAT). PHP. Companion: B_Active_VAT_Pricing_Explainer.docx
A5: WHAT CHANGED IN THIS VERSION
A6: • You are VAT-registered (12%). PH law (DTI all-in pricing) requires displayed price = final price paid — VAT cannot be added at checkout.
A7: • We MARKED UP each price by ~12% so that, after remitting VAT, your take (net-of-VAT) equals the original target margin.
A8: • So: the customer pays more; your profit per unit is preserved. Net-of-VAT base ≈ your old price.
A10: HOW TO READ THE PRICING MODEL TAB
A11: • 'Old price (pre-VAT)' = the previous number (what your margin was modelled on).
A12: • 'NEW price (VAT-incl)' = the new displayed/selling price (blue = the input that drives everything).
A13: • 'Net revenue' = NEW / 1.12 (what you keep before costs; this is the VAT-exclusive base).
A14: • 'Output VAT' = the 12% portion inside the price that you collect and remit to BIR.
A15: • 'Gross margin %' and 'Net contribution' are computed on the NET (VAT-exclusive) revenue — the honest view.
... A26: Source of costs: Barry Active.xlsx. Market bands: research/07_ph_pricing_benchmarks.md. Not tax advice — confirm with your accountant/BIR.

Sheet Assumptions
A1: Assumptions (edit yellow)
A2: Assumption | B2: Unit | C2: Value | D2: Note
A3: VAT rate | B3: % | C3: 0.12 | D3: PH standard VAT
A4: Inbound, branding & freight / unit | B4: ₱ | C4: 150 | D4: From 2nd-batch logo+hangtag+inbound
A5: Packaging / unit | B5: ₱ | C5: 25 | D5: Mailer, tissue, card
A6: Payment processing (blended) | B6: % | C6: 0.025 | D6: PayMongo blended ~2.5% (charged on full collected incl VAT)
A7: Outbound shipping borne / unit | B7: ₱ | C7: 90 | D7: After customer-paid + free-ship mix
A8: Returns/COD RTS allowance / unit | B8: ₱ | C8: 120 | D8: COD bounce + 7-day exchange

Sheet Pricing Model
A1: Pricing Model — VAT-inclusive (₱). Margins computed on net-of-VAT revenue.
A2: SKU | B2: Product | C2: Category | D2: Product cost | E2: Loaded cost | F2: Old price (pre-VAT) | G2: NEW price (VAT-incl) | H2: Net revenue (÷1.12) | I2: Output VAT | J2: Gross profit | K2: Gross margin % | L2: Pay fee | M2: Ship allow | N2: Returns allow | O2: Net contribution | P2: Net margin % | Q2: Customer Δ vs old
A3: YY9141 | B3: The Court Dress | C3: Pickleball Dress | D3: 1012.99 | E3: =D3+Assumptions!$C$4+Assumptions!$C$5 -> 1187.99 | F3: 1950 | G3: 2190 | H3: =G3/(1+Assumptions!$C$3) -> 1955.3571 | I3: =G3-H3 -> 234.64286 | J3: =H3-E3 -> 767.36714 | K3: =J3/H3 -> 0.39244347 | L3: =G3*Assumptions!$C$6 -> 54.75 | M3: =Assumptions!$C$7 -> 90 | N3: =Assumptions!$C$8 -> 120 | O3: =J3-L3-M3-N3 -> 502.61714 | P3: =O3/H3 -> 0.25704621 | Q3: =G3-F3 -> 240
A4: YY8793 | B4: The Rally Dress | C4: Pickleball Dress | D4: 916.57 | E4: =D4+Assumptions!$C$4+Assumptions!$C$5 -> 1091.57 | F4: 1890 | G4: 2150 | H4: =G4/(1+Assumptions!$C$3) -> 1919.6429 | I4: =G4-H4 -> 230.35714 | J4: =H4-E4 -> 828.07286 | K4: =J4/H4 -> 0.43136819 | L4: =G4*Assumptions!$C$6 -> 53.75 | M4: =Assumptions!$C$7 -> 90 | N4: =Assumptions!$C$8 -> 120 | O4: =J4-L4-M4-N4 -> 564.32286 | P4: =O4/H4 -> 0.29397284 | Q4: =G4-F4 -> 260
A5: YY4001 | B5: The Bubble Dress | C5: Pickleball Dress | D5: 1009.09 | E5: =D5+Assumptions!$C$4+Assumptions!$C$5 -> 1184.09 | F5: 2190 | G5: 2490 | H5: =G5/(1+Assumptions!$C$3) -> 2223.2143 | I5: =G5-H5 -> 266.78571 | J5: =H5-E5 -> 1039.1243 | K5: =J5/H5 -> 0.46739727 | L5: =G5*Assumptions!$C$6 -> 62.25 | M5: =Assumptions!$C$7 -> 90 | N5: =Assumptions!$C$8 -> 120 | O5: =J5-L5-M5-N5 -> 766.87429 | P5: =O5/H5 -> 0.34493944 | Q5: =G5-F5 -> 300
A6: AS5019 | B6: The Match Dress | C6: Pickleball Dress | D6: 1085 | E6: =D6+Assumptions!$C$4+Assumptions!$C$5 -> 1260 | F6: 2450 | G6: 2750 | H6: =G6/(1+Assumptions!$C$3) -> 2455.3571 | I6: =G6-H6 -> 294.64286 | J6: =H6-E6 -> 1195.3571 | K6: =J6/H6 -> 0.48683636 | L6: =G6*Assumptions!$C$6 -> 68.75 | M6: =Assumptions!$C$7 -> 90 | N6: =Assumptions!$C$8 -> 120 | O6: =J6-L6-M6-N6 -> 916.60714 | P6: =O6/H6 -> 0.37330909 | Q6: =G6-F6 -> 300
A7: AS5028 | B7: The Serve Dress | C7: Pickleball Dress | D7: 1083.17 | E7: =D7+Assumptions!$C$4+Assumptions!$C$5 -> 1258.17 | F7: 2450 | G7: 2750 | H7: =G7/(1+Assumptions!$C$3) -> 2455.3571 | I7: =G7-H7 -> 294.64286 | J7: =H7-E7 -> 1197.1871 | K7: =J7/H7 -> 0.48758167 | L7: =G7*Assumptions!$C$6 -> 68.75 | M7: =Assumptions!$C$7 -> 90 | N7: =Assumptions!$C$8 -> 120 | O7: =J7-L7-M7-N7 -> 918.43714 | P7: =O7/H7 -> 0.3740544 | Q7: =G7-F7 -> 300
A8: YY9187 | B8: The Eyelet Dress | C8: Pickleball Dress | D8: 1069.03 | E8: =D8+Assumptions!$C$4+Assumptions!$C$5 -> 1244.03 | F8: 2450 | G8: 2750 | H8: =G8/(1+Assumptions!$C$3) -> 2455.3571 | I8: =G8-H8 -> 294.64286 | J8: =H8-E8 -> 1211.3271 | K8: =J8/H8 -> 0.49334051 | L8: =G8*Assumptions!$C$6 -> 68.75 | M8: =Assumptions!$C$7 -> 90 | N8: =Assumptions!$C$8 -> 120 | O8: =J8-L8-M8-N8 -> 932.57714 | P8: =O8/H8 -> 0.37981324 | Q8: =G8-F8 -> 300
A9: AS818 | B9: The Varsity Dress | C9: Pickleball Dress | D9: 1346.9 | E9: =D9+Assumptions!$C$4+Assumptions!$C$5 -> 1521.9 | F9: 2650 | G9: 2990 | H9: =G9/(1+Assumptions!$C$3) -> 2669.6429 | I9: =G9-H9 -> 320.35714 | J9: =H9-E9 -> 1147.7429 | K9: =J9/H9 -> 0.42992375 | L9: =G9*Assumptions!$C$6 -> 74.75 | M9: =Assumptions!$C$7 -> 90 | N9: =Assumptions!$C$8 -> 120 | O9: =J9-L9-M9-N9 -> 862.99286 | P9: =O9/H9 -> 0.32326154 | Q9: =G9-F9 -> 340
A10: AS811 | B10: The Ace Dress | C10: Pickleball Dress | D10: 1317.39 | E10: =D10+Assumptions!$C$4+Assumptions!$C$5 -> 1492.39 | F10: 2650 | G10: 2990 | H10: =G10/(1+Assumptions!$C$3) -> 2669.6429 | I10: =G10-H10 -> 320.35714 | J10: =H10-E10 -> 1177.2529 | K10: =J10/H10 -> 0.44097766 | L10: =G10*Assumptions!$C$6 -> 74.75 | M10: =Assumptions!$C$7 -> 90 | N10: =Assumptions!$C$8 -> 120 | O10: =J10-L10-M10-N10 -> 892.50286 | P10: =O10/H10 -> 0.33431545 | Q10: =G10-F10 -> 340
A11: DK21-015 | B11: The Everyday Skort | C11: Skort | D11: 415.56 | E11: =D11+Assumptions!$C$4+Assumptions!$C$5 -> 590.56 | F11: 990 | G11: 1150 | H11: =G11/(1+Assumptions!$C$3) -> 1026.7857 | I11: =G11-H11 -> 123.21429 | J11: =H11-E11 -> 436.22571 | K11: =J11/H11 -> 0.42484591 | L11: =G11*Assumptions!$C$6 -> 28.75 | M11: =Assumptions!$C$7 -> 90 | N11: =Assumptions!$C$8 -> 120 | O11: =J11-L11-M11-N11 -> 197.47571 | P11: =O11/H11 -> 0.19232417 | Q11: =G11-F11 -> 160
A12: DK251204445 | B12: The Pleated Skort | C12: Skort | D12: 485.94 | E12: =D12+Assumptions!$C$4+Assumptions!$C$5 -> 660.94 | F12: 1090 | G12: 1250 | H12: =G12/(1+Assumptions!$C$3) -> 1116.0714 | I12: =G12-H12 -> 133.92857 | J12: =H12-E12 -> 455.13143 | K12: =J12/H12 -> 0.40779776 | L12: =G12*Assumptions!$C$6 -> 31.25 | M12: =Assumptions!$C$7 -> 90 | N12: =Assumptions!$C$8 -> 120 | O12: =J12-L12-M12-N12 -> 213.88143 | P12: =O12/H12 -> 0.19163776 | Q12: =G12-F12 -> 160
A13: DK240420367 | B13: The Flow Skort | C13: Skort | D13: 500.06 | E13: =D13+Assumptions!$C$4+Assumptions!$C$5 -> 675.06 | F13: 1090 | G13: 1250 | H13: =G13/(1+Assumptions!$C$3) -> 1116.0714 | I13: =G13-H13 -> 133.92857 | J13: =H13-E13 -> 441.01143 | K13: =J13/H13 -> 0.39514624 | L13: =G13*Assumptions!$C$6 -> 31.25 | M13: =Assumptions!$C$7 -> 90 | N13: =Assumptions!$C$8 -> 120 | O13: =J13-L13-M13-N13 -> 199.76143 | P13: =O13/H13 -> 0.17898624 | Q13: =G13-F13 -> 160
A14: D31 | B14: The Breeze Skort | C14: Skort | D14: 614.74 | E14: =D14+Assumptions!$C$4+Assumptions!$C$5 -> 789.74 | F14: 1250 | G14: 1450 | H14: =G14/(1+Assumptions!$C$3) -> 1294.6429 | I14: =G14-H14 -> 155.35714 | J14: =H14-E14 -> 504.90286 | K14: =J14/H14 -> 0.38999393 | L14: =G14*Assumptions!$C$6 -> 36.25 | M14: =Assumptions!$C$7 -> 90 | N14: =Assumptions!$C$8 -> 120 | O14: =J14-L14-M14-N14 -> 258.65286 | P14: =O14/H14 -> 0.19978703 | Q14: =G14-F14 -> 200
... A21: PADDLE-1 | B21: B Active Paddle (single) | C21: Paddle | D21: 835.16 | E21: =D21+Assumptions!$C$4+Assumptions!$C$5 -> 1010.16 | F21: 1890 | G21: 2150 | H21: =G21/(1+Assumptions!$C$3) -> 1919.6429 | I21: =G21-H21 -> 230.35714 | J21: =H21-E21 -> 909.48286 | K21: =J21/H21 -> 0.47377712 | L21: =G21*Assumptions!$C$6 -> 53.75 | M21: =Assumptions!$C$7 -> 90 | N21: =Assumptions!$C$8 -> 120 | O21: =J21-L21-M21-N21 -> 645.73286 | P21: =O21/H21 -> 0.33638177 | Q21: =G21-F21 -> 260
C22: AVERAGE / BLENDED | H22: =AVERAGE(H3:H21) -> 1754.2293 | I22: =AVERAGE(I3:I21) -> 210.50752 | J22: =AVERAGE(J3:J21) -> 780.53774 | K22: =AVERAGE(K3:K21) -> 0.43942226 | O22: =AVERAGE(O3:O21) -> 521.41932 | P22: =AVERAGE(P3:P21) -> 0.27342668 | Q22: =AVERAGE(Q3:Q21) -> 233.42105
B24: Margins are on NET (VAT-exclusive) revenue. Net contribution excludes marketing/CAC and input-VAT credit (see Explainer doc). Output VAT shown here is BEFORE crediting input VAT — actual VAT remitted to BIR is lower.

Sheet Competitor Benchmarks
A1: PH Retail Price Benchmarks by Tier (₱) — research/07. B Active column = NEW VAT-incl.
A2: Category | B2: Local premium | C2: Pickleball/Bench/Decathlon | D2: International (Nike/Lulu) PH | E2: Shopee/Lazada | F2: B Active NEW
A3: Sports bra | B3: 599–1,980 | C3: 299–799 | D3: 1,295–4,400 | E3: 99–1,500 | F3: 1,090
A4: Leggings | B4: 719–1,980 | C4: 399–999 | D4: 1,695–7,360 | E4: 150–1,800 | F4: 1,250–1,350
A5: Tank / top | B5: 599–1,149 | C5: 299–699 | D5: 1,295–2,495 | E5: 149–1,299 | F5: 1,050
A6: Skort | B6: 950–1,600 | C6: 999–1,090 | D6: 2,095–3,095 | E6: 299–1,800 | F6: 1,150–1,490
A7: Pickleball / tennis dress | B7: 899–1,399 | C7: 999–1,500 | D7: 3,495–5,795 | E7: 350–2,500 | F7: 2,150–2,990
A8: 2-piece set | B8: 2,376–3,960 | C8: 799–1,299 | D8: 3,000–8,000+ | E8: 399–3,500 | F8: 2,790
A9: Paddle | B9: — | C9: 2,990–17,690 | D9: — | E9: 400–2,500 | F9: 2,150 / set 3,950
A11: Still clearly below Nike/Lululemon imports and above mass-market, even after VAT markup. Positioning holds.

Sheet Summary
A1: Summary
A2: Metric | B2: Value | C2: Notes
A3: Styles | B3: =COUNTA('Pricing Model'!A3:A21) -> 19 | C3: launch range
A4: Avg gross margin % (net-of-VAT) | B4: ='Pricing Model'!K22 -> 0.43942226 | C4: preserved vs pre-VAT
A5: Avg net contribution % | B5: ='Pricing Model'!P22 -> 0.27342668 | C5: after pay/ship/returns
A6: Avg net contribution / unit | B6: ='Pricing Model'!O22 -> 521.41932 | C6: ₱, pre-marketing
A7: Avg output VAT / unit | B7: ='Pricing Model'!I22 -> 210.50752 | C7: collected; reduced by input-VAT credit
A8: Avg customer price increase | B8: ='Pricing Model'!Q22 -> 233.42105 | C8: ₱ added vs old price (the VAT)

Sheet Product Master
A1: Product Master — NEW VAT-inclusive prices
A2: SKU | B2: Product Name | C2: Category | D2: NEW price ₱ (VAT-incl)
A3: YY9141 | B3: The Court Dress | C3: Pickleball Dress | D3: 2190
A4: YY8793 | B4: The Rally Dress | C4: Pickleball Dress | D4: 2150
A5: YY4001 | B5: The Bubble Dress | C5: Pickleball Dress | D5: 2490
A6: AS5019 | B6: The Match Dress | C6: Pickleball Dress | D6: 2750
A7: AS5028 | B7: The Serve Dress | C7: Pickleball Dress | D7: 2750
A8: YY9187 | B8: The Eyelet Dress | C8: Pickleball Dress | D8: 2750
A9: AS818 | B9: The Varsity Dress | C9: Pickleball Dress | D9: 2990
A10: AS811 | B10: The Ace Dress | C10: Pickleball Dress | D10: 2990
A11: DK21-015 | B11: The Everyday Skort | C11: Skort | D11: 1150
A12: DK251204445 | B12: The Pleated Skort | C12: Skort | D12: 1250
A13: DK240420367 | B13: The Flow Skort | C13: Skort | D13: 1250
A14: D31 | B14: The Breeze Skort | C14: Skort | D14: 1450
... A21: PADDLE-1 | B21: B Active Paddle (single) | C21: Paddle | D21: 2150
